LICENSE
MANIFEST.in
README.md
setup.py
allianceauth_signal_pings.egg-info/PKG-INFO
allianceauth_signal_pings.egg-info/SOURCES.txt
allianceauth_signal_pings.egg-info/dependency_links.txt
allianceauth_signal_pings.egg-info/requires.txt
allianceauth_signal_pings.egg-info/top_level.txt
signalpings/__init__.py
signalpings/admin.py
signalpings/app_settings.py
signalpings/apps.py
signalpings/auth_hooks.py
signalpings/helpers.py
signalpings/models.py
signalpings/signals.py
signalpings/tasks.py
signalpings/tests.py
signalpings/urls.py
signalpings/views.py
signalpings/migrations/0001_initial.py
signalpings/migrations/0002_auto_20200625_0121.py
signalpings/migrations/0003_hrappsignal.py
signalpings/migrations/0004_timersignal_corporation.py
signalpings/migrations/0005_charactersignal_statesignal.py
signalpings/migrations/0006_srpsignal.py
signalpings/migrations/0007_hrappsignal_notify_comments.py
signalpings/migrations/__init__.py